pignet2/__init__.py
pignet2/cli.py
pignet2/core.py
pignet2/utils.py
pignet2/analysis/__init__.py
pignet2/analysis/explain.py
pignet2/ckpt/pda_0.pt
pignet2/ckpt/pda_1.pt
pignet2/ckpt/pda_2.pt
pignet2/ckpt/pda_3.pt
pignet2/config/config_test.yaml
pignet2/config/config_train.yaml
pignet2/config/data/default/casf2016_docking.yaml
pignet2/config/data/default/casf2016_scoring.yaml
pignet2/config/data/default/casf2016_screening.yaml
pignet2/config/data/default/cross.yaml
pignet2/config/data/default/derivative.yaml
pignet2/config/data/default/docking.yaml
pignet2/config/data/default/dude.yaml
pignet2/config/data/default/pda.yaml
pignet2/config/data/default/random.yaml
pignet2/config/data/default/scoring.yaml
pignet2/config/data/messi/baseline.yaml
pignet2/config/data/messi/casf2016_docking.yaml
pignet2/config/data/messi/casf2016_scoring.yaml
pignet2/config/data/messi/casf2016_screening.yaml
pignet2/config/data/messi/cross.yaml
pignet2/config/data/messi/derivative.yaml
pignet2/config/data/messi/docking.yaml
pignet2/config/data/messi/dude.yaml
pignet2/config/data/messi/pda.yaml
pignet2/config/data/messi/random.yaml
pignet2/config/data/messi/scoring.yaml
pignet2/config/model/pignet.yaml
pignet2/config/model/pignet_morse.yaml
pignet2/config/run/test.yaml
pignet2/config/run/train.yaml
pignet2/data/__init__.py
pignet2/data/chem.py
pignet2/data/data.py
pignet2/data/datamodule.py
pignet2/data/utils.py
pignet2/exe/generate_data.py
pignet2/exe/path.py
pignet2/exe/predict.py
pignet2/exe/protonate.py
pignet2/exe/set_cuda.py
pignet2/exe/test.py
pignet2/exe/train.py
pignet2/exe/utils.py
pignet2/models/__init__.py
pignet2/models/physics.py
pignet2/models/pignet.py
pignet2/models/pignet_morse.py
pignet2/models/layers/__init__.py
pignet2/models/layers/gated_gat.py
pignet2/models/layers/interaction_net.py
pignet2-0.0.1.dist-info/licenses/LICENSE
pignet2-0.0.1.dist-info/METADATA
pignet2-0.0.1.dist-info/WHEEL
pignet2-0.0.1.dist-info/entry_points.txt
pignet2-0.0.1.dist-info/top_level.txt
pignet2-0.0.1.dist-info/RECORD
