Metadata-Version: 2.4
Name: pignet2
Version: 0.0.1
Summary: Deep learning framework for protein-ligand binding affinity prediction
Author-email: Seokhyun Moon <mshmjp@kaist.ac.kr>
License-Expression: MIT
Project-URL: Homepage, https://github.com/mseok/PIGNet2
Project-URL: Documentation, https://github.com/mseok/PIGNet2#readme
Project-URL: Repository, https://github.com/mseok/PIGNet2.git
Project-URL: Issues, https://github.com/mseok/PIGNet2/issues
Classifier: Development Status :: 4 - Beta
Classifier: Intended Audience :: Science/Research
Classifier: Topic :: Scientific/Engineering :: Bio-Informatics
Classifier: Topic :: Scientific/Engineering :: Artificial Intelligence
Classifier: Programming Language :: Python :: 3
Classifier: Programming Language :: Python :: 3.10
Classifier: Programming Language :: Python :: 3.11
Classifier: Operating System :: OS Independent
Requires-Python: >=3.10
License-File: LICENSE
Requires-Dist: pandas>=2.3.1
Requires-Dist: scikit-learn>=1.7.1
Requires-Dist: scipy>=1.15.3
Requires-Dist: seaborn>=0.13.2
Requires-Dist: joblib>=1.5.1
Requires-Dist: tqdm>=4.67.1
Requires-Dist: click>=8.2.1
Requires-Dist: biopython>=1.85
Requires-Dist: hydra-core==1.3.2
Requires-Dist: dimorphite-dl==2.0.2
Requires-Dist: pymol-open-source-whl==3.1.0.4
Requires-Dist: numpy==1.26.4
Requires-Dist: matplotlib>=3.10.5
Requires-Dist: rdkit>=2025.3.5
Requires-Dist: torch==2.6.0
Requires-Dist: torch-geometric==2.6.0
Dynamic: license-file
